README.md
collection.py
posts.py
readwa.py
setup.py
uri.py
wauser.py
writeas.py
writeasapi.egg-info/PKG-INFO
writeasapi.egg-info/SOURCES.txt
writeasapi.egg-info/dependency_links.txt
writeasapi.egg-info/requires.txt
writeasapi.egg-info/top_level.txt