Metadata-Version: 1.0
Name: writeasapi
Version: 0.1.9.4.3
Summary: An API client library for Write.as
Home-page: https://github.com/cjeller1592/Writeas-API
Author: CJ Eller
Author-email: cjeller1592@gmail.com
License: MIT
Platform: UNKNOWN
